README
setup.py
src/jldgeo/__init__.py
src/jldgeo/fsm.py
src/jldgeo/main.py
src/jldgeo/state.py
src/jldgeo.egg-info/PKG-INFO
src/jldgeo.egg-info/SOURCES.txt
src/jldgeo.egg-info/dependency_links.txt
src/jldgeo.egg-info/not-zip-safe
src/jldgeo.egg-info/requires.txt
src/jldgeo.egg-info/top_level.txt
src/jldgeo/tests/__init__.py
src/jldgeo/tests/tests.py
src/jldgeo/tests/tests2.py
src/jldjson/__init__.py
src/jldjson/main.py
src/jldjson/tools.py
src/jldjson/tests/__init__.py
src/jldjson/tests/tests.py
src/scripts/jldgeojson
src/scripts/jldjson