Metadata-Version: 1.0
Name: jldgeo
Version: 0.5
Summary: Various geojson/json utilities
Home-page: https://github.com/jldupont/jldgeo
Author: Jean-Lou Dupont
Author-email: jl@jldupont.com
License: UNKNOWN
Platform: UNKNOWN
